Classfile /Users/mac/dev/git/jmh-benchmarks/src/main/java/here/benchmarks/FormatDigitsUtil.class
  Last modified Dec 3, 2018; size 492 bytes
  MD5 checksum 6239bc41cdaed9eedf25d64d95ab1584
  Compiled from "FormatDigitsUtil.java"
final class here.benchmarks.format.FormatDigitsUtil
  minor version: 0
  major version: 55
  flags: (0x0030) ACC_FINAL, ACC_SUPER
  this_class: #6                          // here/benchmarks/FormatDigitsUtil
  super_class: #7                         // java/lang/Object
  interfaces: 0, fields: 0, methods: 2, attributes: 1
Constant pool:
   #1 = Methodref          #7.#16         // java/lang/Object."<init>":()V
   #2 = Class              #17            // java/text/DecimalFormat
   #3 = Methodref          #2.#18         // java/text/DecimalFormat."<init>":(Ljava/lang/String;)V
   #4 = Methodref          #2.#19         // java/text/DecimalFormat.format:(D)Ljava/lang/String;
   #5 = Methodref          #20.#21        // java/lang/Double.parseDouble:(Ljava/lang/String;)D
   #6 = Class              #22            // here/benchmarks/FormatDigitsUtil
   #7 = Class              #23            // java/lang/Object
   #8 = Utf8               <init>
   #9 = Utf8               ()V
  #10 = Utf8               Code
  #11 = Utf8               LineNumberTable
  #12 = Utf8               formatDouble
  #13 = Utf8               (DLjava/lang/String;)D
  #14 = Utf8               SourceFile
  #15 = Utf8               FormatDigitsUtil.java
  #16 = NameAndType        #8:#9          // "<init>":()V
  #17 = Utf8               java/text/DecimalFormat
  #18 = NameAndType        #8:#24         // "<init>":(Ljava/lang/String;)V
  #19 = NameAndType        #25:#26        // format:(D)Ljava/lang/String;
  #20 = Class              #27            // java/lang/Double
  #21 = NameAndType        #28:#29        // parseDouble:(Ljava/lang/String;)D
  #22 = Utf8               here/benchmarks/FormatDigitsUtil
  #23 = Utf8               java/lang/Object
  #24 = Utf8               (Ljava/lang/String;)V
  #25 = Utf8               format
  #26 = Utf8               (D)Ljava/lang/String;
  #27 = Utf8               java/lang/Double
  #28 = Utf8               parseDouble
  #29 = Utf8               (Ljava/lang/String;)D
{
  here.benchmarks.format.FormatDigitsUtil();
    descriptor: ()V
    flags: (0x0000)
    Code:
      stack=1, locals=1, args_size=1
         0: aload_0
         1: invokespecial #1                  // Method java/lang/Object."<init>":()V
         4: return
      LineNumberTable:
        line 6: 0

  static double formatDouble(double, java.lang.String);
    descriptor: (DLjava/lang/String;)D
    flags: (0x0008) ACC_STATIC
    Code:
      stack=3, locals=3, args_size=2
         0: new           #2                  // class java/text/DecimalFormat
         3: dup
         4: aload_2
         5: invokespecial #3                  // Method java/text/DecimalFormat."<init>":(Ljava/lang/String;)V
         8: dload_0
         9: invokevirtual #4                  // Method java/text/DecimalFormat.format:(D)Ljava/lang/String;
        12: invokestatic  #5                  // Method java/lang/Double.parseDouble:(Ljava/lang/String;)D
        15: dreturn
      LineNumberTable:
        line 10: 0
}
SourceFile: "FormatDigitsUtil.java"
